dyndns_to_hetzner/__init__.py
dyndns_to_hetzner-1.0.2.dist-info/licenses/LICENSE
dyndns_to_hetzner-1.0.2.dist-info/METADATA
dyndns_to_hetzner-1.0.2.dist-info/WHEEL
dyndns_to_hetzner-1.0.2.dist-info/top_level.txt
dyndns_to_hetzner-1.0.2.dist-info/RECORD
