Metadata-Version: 2.4
Name: dyndns-to-hetzner
Version: 1.0.2
Summary: DynDNS endpoint translation to Hetzner API
Author-email: Faeyben <kontakt@faeyben.de>
License-Expression: GPL-3.0
Project-URL: Homepage, https://github.com/faeyben/dyndns-to-hetzner
Keywords: dns,dyndns,hetzner
Classifier: Development Status :: 4 - Beta
Classifier: Framework :: Flask
Classifier: Programming Language :: Python :: 3
Requires-Python: >3.9
License-File: LICENSE
Requires-Dist: flask
Requires-Dist: flask_httpauth
Requires-Dist: requests
Requires-Dist: click
Dynamic: license-file
